typingplus.py
typingplus-2.2.3.dist-info/METADATA
typingplus-2.2.3.dist-info/RECORD
typingplus-2.2.3.dist-info/WHEEL
typingplus-2.2.3.dist-info/top_level.txt
