Metadata-Version: 2.1
Name: typingplus
Version: 2.2.3
Summary: An enhanced typing library with casting and validation.
Home-page: https://github.com/contains-io/typingplus
Author: Melissa Nuño
Author-email: dangle@contains.io
License: MIT
Keywords: typing,schemavalidation,types,pep484,annotations,type comments
Platform: UNKNOWN
Classifier: Development Status :: 3 - Alpha
Classifier: License :: OSI Approved :: MIT License
Classifier: Operating System :: OS Independent
Classifier: Programming Language :: Python
Classifier: Programming Language :: Python :: 2
Classifier: Programming Language :: Python :: 2.7
Classifier: Programming Language :: Python :: 3
Classifier: Programming Language :: Python :: 3.4
Classifier: Programming Language :: Python :: 3.5
Classifier: Programming Language :: Python :: 3.6
Classifier: Programming Language :: Python :: 3.7
Classifier: Intended Audience :: Developers
Classifier: Topic :: Software Development
Requires-Dist: six (>=1.10.0)
Requires-Dist: typing (>=3.5.3); python_version < "3.7.0"
Requires-Dist: typing-extensions (>=3.6.2); python_version < "3.7.0"
